transliter/__init__.py
transliter/cyrillic_list.py
transliter/jp_list.py
transliter/ko_jamo.py
transliter/main.py
transliter/spacing.py
transliter/transliter_cyrillic.py
transliter/transliter_jp.py
transliter/transliter_ko.py
transliter-0.4.1.dist-info/LICENSE
transliter-0.4.1.dist-info/METADATA
transliter-0.4.1.dist-info/WHEEL
transliter-0.4.1.dist-info/top_level.txt
transliter-0.4.1.dist-info/RECORD
