Metadata-Version: 2.1
Name: transliter
Version: 0.4.1
Summary: TransLiter transliterates multilingual text into Latin script.
Home-page: https://github.com/elibooklover/Transliter
Author: Hoyeol Kim
Author-email: elibooklover@gmail.com
License: GPL-2.0
Requires-Python: >=3.6
License-File: LICENSE
Requires-Dist: pandas
Requires-Dist: pykakasi
